{"is_source_file": false, "format": "", "description": "", "external_files": [], "external_methods": [], "published": [], "classes": [], "methods": [], "calls": [], "search-terms": [], "state": 2, "file_id": 11, "knowledge_revision": 29, "git_revision": "a8eb6ca3d9a3e51bf20a2937795837e59895b82d", "ctags": [], "hash": "247903a67b7f3b3c3d3c01e473b10ab5", "format-version": 4, "code-base-name": "lovable_backend_api", "filename": "lovable_backend_api/src/schemas/__init__.py", "revision_history": [{"29": "a8eb6ca3d9a3e51bf20a2937795837e59895b82d"}]}